ccai/__init__.py
ccai/__main__.py
ccai/args.py
ccai/main.py
ccai/resources.py
ccai/server.py
ccai/utils.py
ccai/ws.py
ccai/app/favicon.ico
ccai/app/favicon.svg
ccai/app/index.html
ccai/app/notebook.html
ccai/app/static/ansi-to-html/0.7.2/ansi-to-html.js
ccai/app/static/ansi-to-html/0.7.2/ansi-to-html.mjs
ccai/app/static/ccai/ccai.v1.min.css
ccai/app/static/ccai/ccai.v1.min.js
ccai/app/static/ccai/fonts.v1.min.css
ccai/app/static/codemirror-autocomplete/6.18.6/autocomplete.js
ccai/app/static/codemirror-autocomplete/6.18.6/autocomplete.mjs
ccai/app/static/codemirror-commands/6.8.1/commands.js
ccai/app/static/codemirror-commands/6.8.1/commands.mjs
ccai/app/static/codemirror-lang-css/6.3.1/lang-css.js
ccai/app/static/codemirror-lang-css/6.3.1/lang-css.mjs
ccai/app/static/codemirror-lang-html/6.4.9/lang-html.js
ccai/app/static/codemirror-lang-html/6.4.9/lang-html.mjs
ccai/app/static/codemirror-lang-javascript/6.2.4/lang-javascript.js
ccai/app/static/codemirror-lang-javascript/6.2.4/lang-javascript.mjs
ccai/app/static/codemirror-lang-json/6.0.2/lang-json.js
ccai/app/static/codemirror-lang-json/6.0.2/lang-json.mjs
ccai/app/static/codemirror-lang-markdown/6.3.4/lang-markdown.js
ccai/app/static/codemirror-lang-markdown/6.3.4/lang-markdown.mjs
ccai/app/static/codemirror-lang-python/6.2.1/lang-python.js
ccai/app/static/codemirror-lang-python/6.2.1/lang-python.mjs
ccai/app/static/codemirror-language/6.11.3/language.js
ccai/app/static/codemirror-language/6.11.3/language.mjs
ccai/app/static/codemirror-lint/6.8.5/lint.js
ccai/app/static/codemirror-lint/6.8.5/lint.mjs
ccai/app/static/codemirror-search/6.5.11/search.js
ccai/app/static/codemirror-search/6.5.11/search.mjs
ccai/app/static/codemirror-state/6.5.2/state.js
ccai/app/static/codemirror-state/6.5.2/state.mjs
ccai/app/static/codemirror-view/6.38.1/view.js
ccai/app/static/codemirror-view/6.38.1/view.mjs
ccai/app/static/fontawesome/6.7.2/css/fontawesome.min.css
ccai/app/static/fontawesome/6.7.2/css/regular.min.css
closed_circuit_ai-1.0.1.dist-info/licenses/LICENSE
closed_circuit_ai-1.0.1.dist-info/METADATA
closed_circuit_ai-1.0.1.dist-info/WHEEL
closed_circuit_ai-1.0.1.dist-info/entry_points.txt
closed_circuit_ai-1.0.1.dist-info/top_level.txt
closed_circuit_ai-1.0.1.dist-info/RECORD
