Metadata-Version: 2.4
Name: closed-circuit-ai
Version: 1.0.1
Summary: closed-circuit-ai
Author-email: "Reclusive Inc." <contact@reclusive.ai>
License-Expression: MIT
Project-URL: Homepage, https://github.com/Reclusive-Inc/closed-circuit-ai
Classifier: Programming Language :: Python :: 3
Classifier: Programming Language :: Python :: 3.11
Classifier: Operating System :: OS Independent
Requires-Python: >=3.10
License-File: LICENSE
Requires-Dist: fastapi~=0.118.0
Requires-Dist: filelock~=3.19.0
Requires-Dist: httpx~=0.28.0
Requires-Dist: ipykernel~=6.30.0
Requires-Dist: jupyter-client~=8.6.0
Requires-Dist: nbformat~=5.10.0
Requires-Dist: platformdirs~=4.4.0
Requires-Dist: pycrdt~=0.12.0
Requires-Dist: pycrdt-websocket~=0.16.0
Requires-Dist: pydantic~=2.11.0
Requires-Dist: uvicorn~=0.37.0
Requires-Dist: websockets~=15.0.0
Dynamic: license-file
